LICENSE
README.md
setup.py
CVE_2024_0352.egg-info/PKG-INFO
CVE_2024_0352.egg-info/SOURCES.txt
CVE_2024_0352.egg-info/dependency_links.txt
CVE_2024_0352.egg-info/entry_points.txt
CVE_2024_0352.egg-info/requires.txt
CVE_2024_0352.egg-info/top_level.txt
cve20240352/main.py
cve20240352/includes/__init__.py
cve20240352/includes/bot.py
cve20240352/includes/filereader.py
cve20240352/includes/scan.py
cve20240352/includes/writefile.py
cve20240352/utils/__init__.py
cve20240352/utils/configure.py
cve20240352/utils/const.py
cve20240352/utils/helpers.py
cve20240352/utils/status.py